streamlit_component_navbar-0.7.7.dist-info/licenses/LICENSE
streamlit_plugins/components/navbar/__init__.py
streamlit_plugins/components/navbar/config.py
streamlit_plugins/components/navbar/inject_script.py
streamlit_plugins/components/navbar/frontend/build/CrossOriginInterface.js
streamlit_plugins/components/navbar/frontend/build/asset-manifest.json
streamlit_plugins/components/navbar/frontend/build/bootstrap.min.css
streamlit_plugins/components/navbar/frontend/build/bootstrap.min.css.map
streamlit_plugins/components/navbar/frontend/build/index.html
streamlit_plugins/components/navbar/frontend/build/material-fonts.css
streamlit_plugins/components/navbar/frontend/build/material.woff2
streamlit_plugins/components/navbar/frontend/build/st-styles.css
streamlit_plugins/components/navbar/frontend/build/style.css
streamlit_plugins/components/navbar/frontend/build/static/js/main.8bc23bfa.js
streamlit_plugins/components/navbar/frontend/build/static/js/main.8bc23bfa.js.LICENSE.txt
streamlit_plugins/components/navbar/frontend/build/static/js/main.8bc23bfa.js.map
streamlit_plugins/extension/__init__.py
streamlit_plugins/extension/button_group/__init__.py
streamlit_component_navbar-0.7.7.dist-info/METADATA
streamlit_component_navbar-0.7.7.dist-info/WHEEL
streamlit_component_navbar-0.7.7.dist-info/top_level.txt
streamlit_component_navbar-0.7.7.dist-info/RECORD
